[
  {
    "Name": "Gudeta BIRATU",
    "Age": 30,
    "Time": 8145000
  },
  {
    "Name": "Teferi BALCHA",
    "Age": 34,
    "Time": 8156000.00000002
  },
  {
    "Name": "Moses KIBERE",
    "Age": 30,
    "Time": 8179999.99999999
  },
  {
    "Name": "Abel ROP",
    "Age": 30,
    "Time": 8264999.99999999
  },
  {
    "Name": "Ahmed NASEF",
    "Age": 27,
    "Time": 8410000
  },
  {
    "Name": "Patrick MURIUKI",
    "Age": 27,
    "Time": 8529999.99999998
  },
  {
    "Name": "Ismail SENANDJI",
    "Age": 31,
    "Time": 8902000.00000001
  },
  {
    "Name": "Ilia KUCAROV",
    "Age": 31,
    "Time": 8876999.99999999
  },
  {
    "Name": "Shaban MUSTAFA",
    "Age": 39,
    "Time": 9000000
  },
  {
    "Name": "Hasan TURGUT",
    "Age": 25,
    "Time": 9173999.99999999
  },
  {
    "Name": "Milos MOLOVANOVIC",
    "Age": 28,
    "Time": 9221000
  },
  {
    "Name": "Gancho SLAVOV",
    "Age": 41,
    "Time": 9420000.00000001
  },
  {
    "Name": "Rosen LILOV",
    "Age": 43,
    "Time": 9452000.00000002
  },
  {
    "Name": "Patrick KACZYNSKI",
    "Age": 27,
    "Time": 9878000
  },
  {
    "Name": "Srdjan SAMARDZIC",
    "Age": 28,
    "Time": 10133000
  },
  {
    "Name": "Dilyan BOYADZHIEV",
    "Age": 32,
    "Time": 10214000
  },
  {
    "Name": "Milos DRAGOVIC",
    "Age": 24,
    "Time": 10382000
  },
  {
    "Name": "Evgeni VASILEV",
    "Age": 32,
    "Time": 10539000
  },
  {
    "Name": "Nathan ANDREWS",
    "Age": 42,
    "Time": 10618000
  },
  {
    "Name": "Kristian KIRILOV",
    "Age": 24,
    "Time": 10803000
  },
  {
    "Name": "Igor JAKIMOVSKI",
    "Age": 43,
    "Time": 10821000
  },
  {
    "Name": "Vesselin TZOTCHEV",
    "Age": 48,
    "Time": 10788000
  },
  {
    "Name": "Gambini EMANUELE",
    "Age": 47,
    "Time": 10970000
  },
  {
    "Name": "Serioza KUCHUKOV",
    "Age": 62,
    "Time": 10989000
  },
  {
    "Name": "Alexander SPASOV",
    "Age": 24,
    "Time": 11000000
  },
  {
    "Name": "Miroslav FILKOV",
    "Age": 24,
    "Time": 11085000
  },
  {
    "Name": "Borislav BURLAK",
    "Age": 39,
    "Time": 11148000
  },
  {
    "Name": "Danny STONES",
    "Age": 35,
    "Time": 11167000
  },
  {
    "Name": "Martin GRAMATIKOV",
    "Age": 44,
    "Time": 11466000
  },
  {
    "Name": "Ivan TSANOV",
    "Age": 47,
    "Time": 11613000
  },
  {
    "Name": "Stanislav MANEV",
    "Age": 40,
    "Time": 11667000
  },
  {
    "Name": "Ludwig DUCH",
    "Age": 54,
    "Time": 11702000
  },
  {
    "Name": "Dimitar DIMITROV",
    "Age": 28,
    "Time": 11821000
  },
  {
    "Name": "Velichko MANOLOV",
    "Age": 34,
    "Time": 11831000
  },
  {
    "Name": "Mihail STEPANOV",
    "Age": 44,
    "Time": 11959000
  },
  {
    "Name": "Samuel PAPOT",
    "Age": 34,
    "Time": 11969000
  },
  {
    "Name": "Jean-Luc POTIER",
    "Age": 47,
    "Time": 11987000
  },
  {
    "Name": "Christo KABADAEV",
    "Age": 35,
    "Time": 12062000
  },
  {
    "Name": "Pavlin DIMITROV",
    "Age": 44,
    "Time": 12080000
  },
  {
    "Name": "Roumen JORDANOV",
    "Age": 38,
    "Time": 12088000
  },
  {
    "Name": "Svetoslav TRAYKOV",
    "Age": 41,
    "Time": 12208000
  },
  {
    "Name": "Paolo DEAVI",
    "Age": 45,
    "Time": 12292000
  },
  {
    "Name": "Velichko DIMITROV",
    "Age": 55,
    "Time": 12304000
  },
  {
    "Name": "Martin BACHEV",
    "Age": 36,
    "Time": 12314000
  },
  {
    "Name": "Stefan LAZAOV",
    "Age": 30,
    "Time": 12347000
  },
  {
    "Name": "Levant SEBASTIEN",
    "Age": 39,
    "Time": 12352000
  },
  {
    "Name": "Miguel RIBES",
    "Age": 45,
    "Time": 12368000
  },
  {
    "Name": "Didier GENTRIC",
    "Age": 57,
    "Time": 12404000
  },
  {
    "Name": "Boyan BOYCHEV",
    "Age": 46,
    "Time": 12425000
  },
  {
    "Name": "Hristo DOBREV",
    "Age": 30,
    "Time": 12456000
  },
  {
    "Name": "Stanimir DIMITROV",
    "Age": 27,
    "Time": 12456000
  },
  {
    "Name": "Simon HADLEY",
    "Age": 30,
    "Time": 12470000
  },
  {
    "Name": "Andrea MIORI",
    "Age": 50,
    "Time": 12478000
  },
  {
    "Name": "Konstantin PRODANOV",
    "Age": 40,
    "Time": 12507000
  },
  {
    "Name": "Vencislav PETKOV",
    "Age": 35,
    "Time": 12585000
  },
  {
    "Name": "Ivan BESHEV",
    "Age": 35,
    "Time": 12586000
  },
  {
    "Name": "Atanas DIZOV",
    "Age": 43,
    "Time": 12604000
  },
  {
    "Name": "Gillet GERARD",
    "Age": 53,
    "Time": 12619000
  },
  {
    "Name": "Christoph RANDT",
    "Age": 63,
    "Time": 12633000
  },
  {
    "Name": "Georgi SEMKOVSKI",
    "Age": 49,
    "Time": 12649000
  },
  {
    "Name": "Emil IVANOV",
    "Age": 44,
    "Time": 12692000
  },
  {
    "Name": "Ivaylo PETKOV",
    "Age": 33,
    "Time": 12682000
  },
  {
    "Name": "Plamen IVANOV",
    "Age": 54,
    "Time": 12728000
  },
  {
    "Name": "Tim TEEGE",
    "Age": 33,
    "Time": 12718000
  },
  {
    "Name": "Lachezar STOYCHEV",
    "Age": 28,
    "Time": 12743000
  },
  {
    "Name": "Martin CHOY",
    "Age": 28,
    "Time": 12743000
  },
  {
    "Name": "Mihail IVANOV",
    "Age": 28,
    "Time": 12743000
  },
  {
    "Name": "Georgi GEORGIEV",
    "Age": 37,
    "Time": 12735000
  },
  {
    "Name": "Franco PLACUCCI",
    "Age": 60,
    "Time": 12760000
  },
  {
    "Name": "Stephen PARKER",
    "Age": 62,
    "Time": 12754000
  },
  {
    "Name": "Christos FYLLARIDIS",
    "Age": 44,
    "Time": 12806000
  },
  {
    "Name": "Magnus BJOERKLUND",
    "Age": 43,
    "Time": 12865000
  },
  {
    "Name": "Kalin STOYANOV",
    "Age": 29,
    "Time": 12916000
  },
  {
    "Name": "Luben KENANOV",
    "Age": 61,
    "Time": 12938000
  },
  {
    "Name": "Aitor CESPON",
    "Age": 23,
    "Time": 12970000
  },
  {
    "Name": "Stanimir BOROV",
    "Age": 24,
    "Time": 12984000
  },
  {
    "Name": "Zahari HUSEIN",
    "Age": 33,
    "Time": 13008000
  },
  {
    "Name": "Georgi MARINOV",
    "Age": 22,
    "Time": 13042000
  },
  {
    "Name": "Hristo TSVETKOV",
    "Age": 23,
    "Time": 13055000
  },
  {
    "Name": "Ivan BORISOV",
    "Age": 48,
    "Time": 13053000
  },
  {
    "Name": "Daniel KUBASHLIEV",
    "Age": 28,
    "Time": 13076000
  },
  {
    "Name": "Vencislav NEDYALKOV",
    "Age": 32,
    "Time": 13082000
  },
  {
    "Name": "Pierluigi DEBANI",
    "Age": 50,
    "Time": 13104000
  },
  {
    "Name": "Hristo RUMENOV",
    "Age": 34,
    "Time": 13171000
  },
  {
    "Name": "Martin PEPELDZHIYSKI",
    "Age": 34,
    "Time": 13204000
  },
  {
    "Name": "Alexander STOYANOV",
    "Age": 48,
    "Time": 13236000
  },
  {
    "Name": "Tihomir BLAGOEV",
    "Age": 32,
    "Time": 13228000
  },
  {
    "Name": "Velizar BAGAROV",
    "Age": 24,
    "Time": 13260000
  },
  {
    "Name": "Dobri DOBREV",
    "Age": 32,
    "Time": 13254000
  },
  {
    "Name": "Ivan MANCHEV",
    "Age": 28,
    "Time": 13291000
  },
  {
    "Name": "Nikola MARKOV",
    "Age": 28,
    "Time": 13281000
  },
  {
    "Name": "Daniel IVANOV",
    "Age": 27,
    "Time": 13285000
  },
  {
    "Name": "Migot PATRICE",
    "Age": 43,
    "Time": 13394000
  },
  {
    "Name": "Grigor VARBANOV",
    "Age": 37,
    "Time": 13406000
  },
  {
    "Name": "Petyo NIKOLOV",
    "Age": 44,
    "Time": 13394000
  },
  {
    "Name": "Mitko KLYAVKOV",
    "Age": 51,
    "Time": 13421000
  },
  {
    "Name": "Martin BLOMQVIST",
    "Age": 33,
    "Time": 13452000
  },
  {
    "Name": "Jean MARDUEL",
    "Age": 58,
    "Time": 13460000
  },
  {
    "Name": "Philippe WAROUX",
    "Age": 48,
    "Time": 13459000
  },
  {
    "Name": "Christos ZILOUDIS",
    "Age": 57,
    "Time": 13487000
  },
  {
    "Name": "Stergios MATSIOS",
    "Age": 52,
    "Time": 13489000
  },
  {
    "Name": "Momchil NAIDENOV",
    "Age": 35,
    "Time": 13493000
  },
  {
    "Name": "Martin MORGAN",
    "Age": 62,
    "Time": 13557000
  },
  {
    "Name": "Dimitar BONCHEV",
    "Age": 48,
    "Time": 13576000
  },
  {
    "Name": "Simeon CHERVENKOV",
    "Age": 28,
    "Time": 13589000
  },
  {
    "Name": "Lyubomir TODOROV",
    "Age": 27,
    "Time": 13589000
  },
  {
    "Name": "Lubomir MARINOV",
    "Age": 39,
    "Time": 13642000
  },
  {
    "Name": "Pierluigi PARPINEL",
    "Age": 50,
    "Time": 13711000
  },
  {
    "Name": "Anton DOBREV",
    "Age": 54,
    "Time": 13775000
  },
  {
    "Name": "Plamen VALCHEV",
    "Age": 51,
    "Time": 13793000
  },
  {
    "Name": "Strahil DIMITROV",
    "Age": 22,
    "Time": 13794000
  },
  {
    "Name": "Rumen MANEV",
    "Age": 28,
    "Time": 13802000
  },
  {
    "Name": "Hristo GOCHEV",
    "Age": 29,
    "Time": 13802000
  },
  {
    "Name": "Vladimir VLADIMIROV",
    "Age": 48,
    "Time": 13834000
  },
  {
    "Name": "Danail RANGELOV",
    "Age": 43,
    "Time": 13838000
  },
  {
    "Name": "Ryszard ELLERT",
    "Age": 58,
    "Time": 13846000
  },
  {
    "Name": "Sergio LOPEZ",
    "Age": 25,
    "Time": 13866000
  },
  {
    "Name": "Todor DIMITROV",
    "Age": 42,
    "Time": 13872000
  },
  {
    "Name": "Alexander NAIDENOV",
    "Age": 58,
    "Time": 13883000
  },
  {
    "Name": "Francesco FERRUCCI",
    "Age": 45,
    "Time": 13888000
  },
  {
    "Name": "Boyan YORDANOV",
    "Age": 38,
    "Time": 13899000
  },
  {
    "Name": "Mihail OGNYANOV",
    "Age": 33,
    "Time": 13949000
  },
  {
    "Name": "Liam ROYLE",
    "Age": 27,
    "Time": 13953000
  },
  {
    "Name": "Ivan KOSTOV",
    "Age": 26,
    "Time": 13988000
  },
  {
    "Name": "Slavi SAVOV",
    "Age": 46,
    "Time": 13987000
  },
  {
    "Name": "Stephen PRICE",
    "Age": 58,
    "Time": 14003000
  },
  {
    "Name": "Vojislav CURULIC",
    "Age": 64,
    "Time": 14061000
  },
  {
    "Name": "Boris CHAKALOV",
    "Age": 29,
    "Time": 14056000
  },
  {
    "Name": "Andreas PALERAS",
    "Age": 40,
    "Time": 14089000
  },
  {
    "Name": "John KINCHEN",
    "Age": 55,
    "Time": 14123000
  },
  {
    "Name": "Nikolay TANKOV",
    "Age": 46,
    "Time": 14126000
  },
  {
    "Name": "Kenneth SCHOOTEN",
    "Age": 49,
    "Time": 14065000
  },
  {
    "Name": "Borislav KAPUKARANOV",
    "Age": 30,
    "Time": 14138000
  },
  {
    "Name": "Reinhold LOPATKA",
    "Age": 57,
    "Time": 14151000
  },
  {
    "Name": "Jann HOFFMANN",
    "Age": 46,
    "Time": 14138000
  },
  {
    "Name": "Ivan MITOVSKI",
    "Age": 26,
    "Time": 14154000
  },
  {
    "Name": "Marian DIMITROV",
    "Age": 29,
    "Time": 14157000
  },
  {
    "Name": "Dimitar DIMKIN",
    "Age": 32,
    "Time": 14154000
  },
  {
    "Name": "Ivan GRAHOVSKI",
    "Age": 20,
    "Time": 14154000
  },
  {
    "Name": "Ivan IVANOV",
    "Age": 30,
    "Time": 14167000
  },
  {
    "Name": "Lachezar CHOLAKOV",
    "Age": 40,
    "Time": 14234000
  },
  {
    "Name": "Miroslav KUTEV",
    "Age": 43,
    "Time": 14238000
  },
  {
    "Name": "David GOODWIN",
    "Age": 50,
    "Time": 14313000
  },
  {
    "Name": "Hristo DIMITROV",
    "Age": 53,
    "Time": 14347000
  },
  {
    "Name": "Kiril DIMITROV",
    "Age": 46,
    "Time": 14334000
  },
  {
    "Name": "Nikola PENCHEV",
    "Age": 28,
    "Time": 14341000
  },
  {
    "Name": "Dalo PASQUALE",
    "Age": 58,
    "Time": 14403000
  },
  {
    "Name": "Colin LONGWORTH",
    "Age": 64,
    "Time": 14447000
  },
  {
    "Name": "Todor PATARLIEV",
    "Age": 35,
    "Time": 14475000
  },
  {
    "Name": "Hassan MOUTRIBI",
    "Age": 47,
    "Time": 14510000
  },
  {
    "Name": "Vincent ZWICKERT",
    "Age": 52,
    "Time": 14511000
  },
  {
    "Name": "Atanas ATANASSOV",
    "Age": 45,
    "Time": 14524000
  },
  {
    "Name": "James HOLLAND",
    "Age": 45,
    "Time": 14532000
  },
  {
    "Name": "Bernie PRIEKULIS",
    "Age": 61,
    "Time": 14532000
  },
  {
    "Name": "Dmitri MOMOTOV",
    "Age": 30,
    "Time": 14584000
  },
  {
    "Name": "Ivan STOYANOV",
    "Age": 41,
    "Time": 14607000
  },
  {
    "Name": "Michael GORZINSKI",
    "Age": 29,
    "Time": 14511000
  },
  {
    "Name": "Dimoutis PANTELIS",
    "Age": 54,
    "Time": 14634000
  },
  {
    "Name": "Robert HARRIS",
    "Age": 57,
    "Time": 14666000
  },
  {
    "Name": "Nikolay KRASTEVA",
    "Age": 32,
    "Time": 14692000
  },
  {
    "Name": "Dimitar YANKOV",
    "Age": 31,
    "Time": 14697000
  },
  {
    "Name": "Plamen SLAVOV",
    "Age": 33,
    "Time": 14714000
  },
  {
    "Name": "Krasimir MILUSHEV",
    "Age": 30,
    "Time": 14726000
  },
  {
    "Name": "Stefan URILSKI",
    "Age": 48,
    "Time": 14745000
  },
  {
    "Name": "Jeremy HASLETT",
    "Age": 58,
    "Time": 14764000
  },
  {
    "Name": "Ivo TZANKOV",
    "Age": 53,
    "Time": 14826000
  },
  {
    "Name": "Stefan TODOROV",
    "Age": 37,
    "Time": 14831000
  },
  {
    "Name": "Aleksey VASILEV",
    "Age": 48,
    "Time": 14847000
  },
  {
    "Name": "Emmanuel ROUX",
    "Age": 42,
    "Time": 14861000
  },
  {
    "Name": "Plamen ALEXIEV",
    "Age": 29,
    "Time": 14924000
  },
  {
    "Name": "Alfred DEBONO",
    "Age": 69,
    "Time": 14906000
  },
  {
    "Name": "Gary OBRIEN",
    "Age": 53,
    "Time": 14926000
  },
  {
    "Name": "Kalin BOEVSKI",
    "Age": 34,
    "Time": 14929000
  },
  {
    "Name": "Krasimir LYUBOMIROV",
    "Age": 42,
    "Time": 14945000
  },
  {
    "Name": "Radi MILEV",
    "Age": 69,
    "Time": 14976000
  },
  {
    "Name": "Georgi KOLEV",
    "Age": 52,
    "Time": 14989000
  },
  {
    "Name": "Jose MONTON-CRUZ",
    "Age": 35,
    "Time": 15010000
  },
  {
    "Name": "Hristiyan DIMITROV",
    "Age": 27,
    "Time": 14996000
  },
  {
    "Name": "Stanislav RADKOV",
    "Age": 28,
    "Time": 14996000
  },
  {
    "Name": "Daniel DILKOV",
    "Age": 28,
    "Time": 15035000
  },
  {
    "Name": "Plamen PENOV",
    "Age": 27,
    "Time": 15073000
  },
  {
    "Name": "Mario RICCI",
    "Age": 59,
    "Time": 15082000
  },
  {
    "Name": "Cotinaut PHILIPPE",
    "Age": 47,
    "Time": 15136000
  },
  {
    "Name": "Bojan ALEKSIC",
    "Age": 34,
    "Time": 15168000
  },
  {
    "Name": "Emil EVTIMOV",
    "Age": 28,
    "Time": 15205000
  },
  {
    "Name": "Yordan ILIEV",
    "Age": 30,
    "Time": 15205000
  },
  {
    "Name": "Morten BLOCK",
    "Age": 36,
    "Time": 15214000
  },
  {
    "Name": "Angelo CARICATO",
    "Age": 52,
    "Time": 15231000
  },
  {
    "Name": "Ivan RADEV",
    "Age": 36,
    "Time": 15262000
  },
  {
    "Name": "Hristo STOIANOV",
    "Age": 32,
    "Time": 15262000
  },
  {
    "Name": "Ivelin YONKOV",
    "Age": 43,
    "Time": 15279000
  },
  {
    "Name": "Rosen RUSEV",
    "Age": 27,
    "Time": 15283000
  },
  {
    "Name": "Martin RALKOVSKI",
    "Age": 41,
    "Time": 15289000
  },
  {
    "Name": "Volen MLADENOV",
    "Age": 32,
    "Time": 15325000
  },
  {
    "Name": "Alexander DOMNANOVICH",
    "Age": 41,
    "Time": 15326000
  },
  {
    "Name": "Veroslav TEOPHILOV",
    "Age": 37,
    "Time": 15395000
  },
  {
    "Name": "Ivan STANCHEV",
    "Age": 50,
    "Time": 15404000
  },
  {
    "Name": "Aragon BLAI",
    "Age": 42,
    "Time": 15414000
  },
  {
    "Name": "Pedro RAMOS",
    "Age": 44,
    "Time": 15415000
  },
  {
    "Name": "Lyudmil ATANASOV",
    "Age": 33,
    "Time": 15433000
  },
  {
    "Name": "Bernhard HERTINGER",
    "Age": 62,
    "Time": 15459000
  },
  {
    "Name": "Ventsislav TRIFONOV",
    "Age": 49,
    "Time": 15463000
  },
  {
    "Name": "Stefan SHIVAROV",
    "Age": 35,
    "Time": 15608000
  },
  {
    "Name": "Vittorio CERQUENI",
    "Age": 61,
    "Time": 15629000
  },
  {
    "Name": "Dobromir GEORGIEV",
    "Age": 35,
    "Time": 15771000
  },
  {
    "Name": "Igor IGNATOV",
    "Age": 48,
    "Time": 15719000
  },
  {
    "Name": "Tcanio ARABADJIEV",
    "Age": 56,
    "Time": 15854000
  },
  {
    "Name": "Gerald SCHUMANN",
    "Age": 59,
    "Time": 15888000
  },
  {
    "Name": "Michele CRESCENTINI",
    "Age": 46,
    "Time": 15905000
  },
  {
    "Name": "Tsvetan GEORGIEV",
    "Age": 26,
    "Time": 15928000
  },
  {
    "Name": "Stanislav IVANOV",
    "Age": 43,
    "Time": 16056000
  },
  {
    "Name": "Benjamin KANE",
    "Age": 33,
    "Time": 16054000
  },
  {
    "Name": "Momchil DIMITROV",
    "Age": 25,
    "Time": 16070000
  },
  {
    "Name": "Georgi STOYCHEV",
    "Age": 24,
    "Time": 16189000
  },
  {
    "Name": "Krassimir TRENEV",
    "Age": 47,
    "Time": 16169000
  },
  {
    "Name": "Martin SIMEONOV",
    "Age": 27,
    "Time": 16232000
  },
  {
    "Name": "Borislav BUMBAROV",
    "Age": 42,
    "Time": 16260000
  },
  {
    "Name": "Simeon PETKOV",
    "Age": 33,
    "Time": 16345000
  },
  {
    "Name": "Iskren STANEV",
    "Age": 49,
    "Time": 16345000
  },
  {
    "Name": "Guido CAMPEDELLI",
    "Age": 67,
    "Time": 16358000
  },
  {
    "Name": "Anton ANDONOV",
    "Age": 32,
    "Time": 16398000
  },
  {
    "Name": "Esa NIEMINEN",
    "Age": 62,
    "Time": 16408000
  },
  {
    "Name": "Daniel YORDANOV",
    "Age": 48,
    "Time": 16524000
  },
  {
    "Name": "Georgi CHOLAKOV",
    "Age": 29,
    "Time": 16569000
  },
  {
    "Name": "Klaus NEUMANN",
    "Age": 65,
    "Time": 16587000
  },
  {
    "Name": "Boris KACHOV",
    "Age": 71,
    "Time": 16641000
  },
  {
    "Name": "Mladen DENKOV",
    "Age": 25,
    "Time": 16694000
  },
  {
    "Name": "Dobri STEFANOV",
    "Age": 35,
    "Time": 16723000
  },
  {
    "Name": "Detelin HRISTOV",
    "Age": 35,
    "Time": 16716000
  },
  {
    "Name": "Momchil TODOROV",
    "Age": 35,
    "Time": 16836000
  },
  {
    "Name": "Mauri VALAMA",
    "Age": 72,
    "Time": 16863000
  },
  {
    "Name": "Jorma KURITTU",
    "Age": 63,
    "Time": 16866000
  },
  {
    "Name": "Dimitar SHALVARDZIEV",
    "Age": 30,
    "Time": 16940000
  },
  {
    "Name": "Ivan IVANOV",
    "Age": 38,
    "Time": 16993000
  },
  {
    "Name": "Deyan TERZIEV",
    "Age": 45,
    "Time": 17146000
  },
  {
    "Name": "Toshko TODOROV",
    "Age": 23,
    "Time": 17230000
  },
  {
    "Name": "Dimitrii AKCHARLIEV",
    "Age": 66,
    "Time": 17254000
  },
  {
    "Name": "Klaus-Peter ULMSCHNEIDER",
    "Age": 55,
    "Time": 17271000
  },
  {
    "Name": "Yasen KIRILOV",
    "Age": 29,
    "Time": 17361000
  },
  {
    "Name": "Unto LEINIKKA",
    "Age": 65,
    "Time": 17389000
  },
  {
    "Name": "Vasileios KYRILLIDIS",
    "Age": 59,
    "Time": 17401000
  },
  {
    "Name": "Ivelin PARVANOV",
    "Age": 44,
    "Time": 17586000
  },
  {
    "Name": "Milen TZANOV",
    "Age": 42,
    "Time": 17647000
  },
  {
    "Name": "Stefan STOYANOV",
    "Age": 63,
    "Time": 17780000
  },
  {
    "Name": "Boris VASILEV",
    "Age": 29,
    "Time": 17780000
  },
  {
    "Name": "Galin BORISOV",
    "Age": 32,
    "Time": 17795000
  },
  {
    "Name": "Nikola GRIGOROV",
    "Age": 27,
    "Time": 17823000
  },
  {
    "Name": "George ANDONOV",
    "Age": 46,
    "Time": 17828000
  },
  {
    "Name": "Migaud PIERRE",
    "Age": 72,
    "Time": 17883000
  },
  {
    "Name": "Uve STRIMANN",
    "Age": 61,
    "Time": 18036000
  },
  {
    "Name": "Ivan YOSIFOV",
    "Age": 35,
    "Time": 18076000
  },
  {
    "Name": "Ivan DIMOV",
    "Age": 45,
    "Time": 18378000
  },
  {
    "Name": "Alexander DANCHEV",
    "Age": 43,
    "Time": 18463000
  },
  {
    "Name": "Erhard FILTENBORG",
    "Age": 78,
    "Time": 18467000
  },
  {
    "Name": "Wudarski ARKADIUSZ",
    "Age": 45,
    "Time": 18556000
  },
  {
    "Name": "Krum KOSHAREVSKY",
    "Age": 49,
    "Time": 18558000
  },
  {
    "Name": "Ignat GEORGIEV",
    "Age": 26,
    "Time": 18094000
  },
  {
    "Name": "Georgi KRUMOV",
    "Age": 25,
    "Time": 18856000
  },
  {
    "Name": "Georgi SEIZOV",
    "Age": 79,
    "Time": 18958000
  },
  {
    "Name": "Shuhei TAKAHASHI",
    "Age": 28,
    "Time": 18957000
  },
  {
    "Name": "Ivo TEODOSSIEV",
    "Age": 33,
    "Time": 19051000
  },
  {
    "Name": "Miroslav GROZEV",
    "Age": 32,
    "Time": 19041000
  },
  {
    "Name": "Valter BARTOLINI",
    "Age": 60,
    "Time": 19110000
  },
  {
    "Name": "Maurice SANGAN",
    "Age": 63,
    "Time": 19133000
  },
  {
    "Name": "Nikolay GEORGIEV",
    "Age": 34,
    "Time": 19130000
  },
  {
    "Name": "Borislav YANKOV",
    "Age": 64,
    "Time": 19159000
  },
  {
    "Name": "Pekka AIRAKSINEN",
    "Age": 67,
    "Time": 19173000
  },
  {
    "Name": "Stanimir ILIEV",
    "Age": 37,
    "Time": 19201000
  },
  {
    "Name": "JEAN Belle",
    "Age": 52,
    "Time": 19647000
  },
  {
    "Name": "Milen CHECHEV",
    "Age": 33,
    "Time": 20058000
  },
  {
    "Name": "Dimitar KYUSHEV",
    "Age": 46,
    "Time": 20287000
  },
  {
    "Name": "Petar PETROV",
    "Age": 81,
    "Time": 21478000
  }
]